Metadata-Version: 2.1
Name: py-simple-morse-code
Version: 0.0.5
Summary: A python module for interacting with morse code with live decoding feature.
Author-email: Andrew Spangler <AndrewSpangler@users.noreply.github.com>
License: LICENSE
Project-URL: homepage, https://GitHub.com/AndrewSpangler/py_simple_morse_code/
Project-URL: bug tracker, https://GitHub.com/AndrewSpangler/py_simple_morse_code/issues
Project-URL: documentation, https://GitHub.com/AndrewSpangler/py_simple_morse_code/
Project-URL: repository, https://GitHub.com/AndrewSpangler/py_simple_morse_code/
Classifier: Development Status :: 1 - Planning
Classifier: Environment :: Console
Classifier: License :: OSI Approved :: GNU General Public License v3 or later (GPLv3+)
Classifier: Natural Language :: English
Classifier: Operating System :: OS Independent
Classifier: Programming Language :: Python :: 3.11
Requires-Python: >=3.7
License-File: LICENSE
Requires-Dist: pyaudio
Requires-Dist: scipy
Requires-Dist: numpy
